exploretransform/__init__.py
exploretransform/_exploretransform.py
exploretransform-1.0.7.dist-info/LICENSE
exploretransform-1.0.7.dist-info/METADATA
exploretransform-1.0.7.dist-info/WHEEL
exploretransform-1.0.7.dist-info/top_level.txt
exploretransform-1.0.7.dist-info/RECORD
