Metadata-Version: 2.1
Name: exploretransform
Version: 1.0.7
Summary: Explore and transform your data
Home-page: https://github.com/bxp151/exploretransform
Author: Brian Pietracatella
Author-email: bpietrac@gmail.com
License: UNKNOWN
Platform: UNKNOWN
Classifier: Programming Language :: Python :: 3
Classifier: License :: OSI Approved :: MIT License
Classifier: Operating System :: OS Independent
Requires-Python: >=3.6.9
Requires-Dist: numpy
Requires-Dist: pandas
Requires-Dist: plotnine
Requires-Dist: scipy
Requires-Dist: sklearn
Requires-Dist: minepy
Requires-Dist: dcor
